fastapicord/__init__.py
fastapicord-0.0.1.dist-info/LICENSE
fastapicord-0.0.1.dist-info/METADATA
fastapicord-0.0.1.dist-info/WHEEL
fastapicord-0.0.1.dist-info/top_level.txt
fastapicord-0.0.1.dist-info/RECORD
