Metadata-Version: 2.1
Name: fastapicord
Version: 0.0.1
Summary: A Discord Interactions Bot API wrapper that uses FastAPI.
Author-email: Isabelle <isabelle@weeb.email>
Project-URL: Homepage, https://github.com/Isabe1le/fastapicord
Project-URL: Bug Tracker, https://github.com/Isabe1le/fastapicord/issues
Classifier: Programming Language :: Python :: 3
Classifier: License :: OSI Approved :: MIT License
Classifier: Operating System :: OS Independent
Requires-Python: >=3.7
License-File: LICENSE
